olpy/__init__.py
olpy/__main__.py
olpy/classifiers/__base.py
olpy/classifiers/__init__.py
olpy/classifiers/alma.py
olpy/classifiers/aromma.py
olpy/classifiers/arow.py
olpy/classifiers/cw.py
olpy/classifiers/eccw.py
olpy/classifiers/iellip.py
olpy/classifiers/narow.py
olpy/classifiers/nherd.py
olpy/classifiers/ogd.py
olpy/classifiers/pa.py
olpy/classifiers/pa1.py
olpy/classifiers/pa2.py
olpy/classifiers/perceptron.py
olpy/classifiers/romma.py
olpy/classifiers/scw.py
olpy/classifiers/scw2.py
olpy/classifiers/sop.py
olpy/datasets/__init__.py
olpy/datasets/dataset.py
olpy/datasets/loaders.py
olpy/datasets/data/a1a
olpy/datasets/data/a1a.t
olpy/datasets/data/svmguide1
olpy/datasets/data/svmguide1.t
olpy/datasets/data/svmguide3
olpy/datasets/data/svmguide3.t
olpy/exceptions/__init__.py
olpy/exceptions/not_fitted.py
olpy/preprocessing/__init__.py
olpy/preprocessing/labels.py
olpy/utils/__init__.py
olpy-1.0.0.dev3.dist-info/LICENSE
olpy-1.0.0.dev3.dist-info/METADATA
olpy-1.0.0.dev3.dist-info/WHEEL
olpy-1.0.0.dev3.dist-info/top_level.txt
olpy-1.0.0.dev3.dist-info/RECORD
