Metadata-Version: 2.1
Name: olpy
Version: 1.0.0.dev3
Summary: An online machine learning package for Python
Home-page: https://github.com/boladjivinny/olpy
Author: Boladji Vinny
Author-email: vinny.adjibi@outlook.com
License: UNKNOWN
Platform: UNKNOWN
Classifier: Programming Language :: Python :: 3
Classifier: License :: OSI Approved :: MIT License
Classifier: Operating System :: OS Independent
Requires-Python: >=3.6
Requires-Dist: numpy (>=1.20.1)
Requires-Dist: pandas (>=1.1.3)
Requires-Dist: scikit-learn (>=0.24.1)
